odoo/addons/account_payment_method_fs_storage/README.rst
odoo/addons/account_payment_method_fs_storage/__init__.py
odoo/addons/account_payment_method_fs_storage/__manifest__.py
odoo/addons/account_payment_method_fs_storage/i18n/account_payment_method_fs_storage.pot
odoo/addons/account_payment_method_fs_storage/i18n/es.po
odoo/addons/account_payment_method_fs_storage/i18n/it.po
odoo/addons/account_payment_method_fs_storage/models/__init__.py
odoo/addons/account_payment_method_fs_storage/models/account_payment_method.py
odoo/addons/account_payment_method_fs_storage/models/account_payment_order.py
odoo/addons/account_payment_method_fs_storage/models/fs_storage.py
odoo/addons/account_payment_method_fs_storage/readme/CONFIGURE.rst
odoo/addons/account_payment_method_fs_storage/readme/CONTRIBUTORS.rst
odoo/addons/account_payment_method_fs_storage/readme/DESCRIPTION.rst
odoo/addons/account_payment_method_fs_storage/readme/INSTALL.rst
odoo/addons/account_payment_method_fs_storage/readme/USAGE.rst
odoo/addons/account_payment_method_fs_storage/static/description/icon.png
odoo/addons/account_payment_method_fs_storage/static/description/index.html
odoo/addons/account_payment_method_fs_storage/tests/__init__.py
odoo/addons/account_payment_method_fs_storage/tests/test_account_payment_method_fs_storage.py
odoo/addons/account_payment_method_fs_storage/views/account_payment_method.xml
odoo/addons/account_payment_method_fs_storage/views/fs_storage.xml
odoo_addon_account_payment_method_fs_storage-16.0.1.0.3.dist-info/METADATA
odoo_addon_account_payment_method_fs_storage-16.0.1.0.3.dist-info/WHEEL
odoo_addon_account_payment_method_fs_storage-16.0.1.0.3.dist-info/top_level.txt
odoo_addon_account_payment_method_fs_storage-16.0.1.0.3.dist-info/RECORD
