Metadata-Version: 2.1
Name: odoo-addon-account_payment_method_fs_storage
Version: 16.0.1.0.3
Summary: Add the possibility to specify on the payment method, a storage where files generated will be pushed to upon payment
Home-page: https://github.com/OCA/bank-payment
Author: ACSONE SA/NV,Odoo Community Association (OCA)
Author-email: support@odoo-community.org
License: AGPL-3
Classifier: Programming Language :: Python
Classifier: Framework :: Odoo
Classifier: Framework :: Odoo :: 16.0
Classifier: License :: OSI Approved :: GNU Affero General Public License v3
Requires-Python: >=3.10
Requires-Dist: odoo-addon-account-banking-sepa-credit-transfer<16.1dev,>=16.0dev
Requires-Dist: odoo-addon-fs-storage<16.1dev,>=16.0dev
Requires-Dist: odoo<16.1dev,>=16.0a
